README.rst
setup.py
searx/__init__.py
searx/autocomplete.py
searx/brand.py
searx/exceptions.py
searx/external_bang.py
searx/languages.py
searx/poolrequests.py
searx/preferences.py
searx/query.py
searx/results.py
searx/search.py
searx/settings.yml
searx/testing.py
searx/url_utils.py
searx/utils.py
searx/version.py
searx/webapp.py
searx.egg-info/PKG-INFO
searx.egg-info/SOURCES.txt
searx.egg-info/dependency_links.txt
searx.egg-info/entry_points.txt
searx.egg-info/not-zip-safe
searx.egg-info/requires.txt
searx.egg-info/top_level.txt
searx/../README.rst
searx/../requirements-dev.txt
searx/../requirements.txt
searx/answerers/__init__.py
searx/data/bangs.json
searx/data/currencies.json
searx/data/engines_languages.json
searx/data/useragents.json
searx/engines/1337x.py
searx/engines/__init__.py
searx/engines/acgsou.py
searx/engines/apkmirror.py
searx/engines/archlinux.py
searx/engines/arxiv.py
searx/engines/base.py
searx/engines/bing.py
searx/engines/bing_images.py
searx/engines/bing_news.py
searx/engines/bing_videos.py
searx/engines/btdigg.py
searx/engines/currency_convert.py
searx/engines/dailymotion.py
searx/engines/deezer.py
searx/engines/deviantart.py
searx/engines/dictzone.py
searx/engines/digbt.py
searx/engines/digg.py
searx/engines/doku.py
searx/engines/duckduckgo.py
searx/engines/duckduckgo_definitions.py
searx/engines/duckduckgo_images.py
searx/engines/duden.py
searx/engines/dummy-offline.py
searx/engines/dummy.py
searx/engines/etools.py
searx/engines/fdroid.py
searx/engines/filecrop.py
searx/engines/flickr.py
searx/engines/flickr_noapi.py
searx/engines/framalibre.py
searx/engines/frinkiac.py
searx/engines/genius.py
searx/engines/gentoo.py
searx/engines/gigablast.py
searx/engines/github.py
searx/engines/google.py
searx/engines/google_images.py
searx/engines/google_news.py
searx/engines/google_videos.py
searx/engines/ina.py
searx/engines/invidious.py
searx/engines/json_engine.py
searx/engines/kickass.py
searx/engines/mediawiki.py
searx/engines/microsoft_academic.py
searx/engines/mixcloud.py
searx/engines/nyaa.py
searx/engines/openstreetmap.py
searx/engines/pdbe.py
searx/engines/photon.py
searx/engines/piratebay.py
searx/engines/pubmed.py
searx/engines/qwant.py
