Metadata-Version: 2.1
Name: searx
Version: 0.17.0
Summary: A privacy-respecting, hackable metasearch engine
Home-page: https://asciimoo.github.io/searx
Author: Adam Tauber
Author-email: asciimoo@gmail.com
License: GNU Affero General Public License
Project-URL: Issue tracker, https://github.com/asciimoo/searx/issues
Project-URL: Code, https://github.com/asciimoo/searx
Keywords: metasearch searchengine search web http
Platform: UNKNOWN
Classifier: Development Status :: 4 - Beta
Classifier: Programming Language :: Python
Classifier: Topic :: Internet
Classifier: Topic :: Internet :: WWW/HTTP :: HTTP Servers
Classifier: Topic :: Internet :: WWW/HTTP :: WSGI :: Application
Classifier: License :: OSI Approved :: GNU Affero General Public License v3
Provides-Extra: test
